dynamic_agent_switcher/__init__.py
dynamic_agent_switcher/agent_wrapper.py
dynamic_agent_switcher/conditions.py
dynamic_agent_switcher/rate_limiter.py
dynamic_agent_switcher/switcher.py
dynamic_agent_switcher-0.1.1.dist-info/licenses/LICENSE
dynamic_agent_switcher-0.1.1.dist-info/METADATA
dynamic_agent_switcher-0.1.1.dist-info/WHEEL
dynamic_agent_switcher-0.1.1.dist-info/top_level.txt
dynamic_agent_switcher-0.1.1.dist-info/RECORD
