Metadata-Version: 2.4
Name: dynamic_agent_switcher
Version: 0.1.1
Summary: A flexible package for switching AI models during agent execution
Home-page: https://github.com/sumitpaul/dynamic-agent-switcher
Author: Sumit Paul
Author-email: Sumit Paul <sumit.18.paul@gmail.com>
Maintainer-email: Sumit Paul <sumit.18.paul@gmail.com>
License: MIT
Project-URL: Homepage, https://github.com/sumitpaul/dynamic-agent-switcher
Project-URL: Documentation, https://github.com/sumitpaul/dynamic-agent-switcher#readme
Project-URL: Repository, https://github.com/sumitpaul/dynamic-agent-switcher
Project-URL: Bug Tracker, https://github.com/sumitpaul/dynamic-agent-switcher/issues
Keywords: ai,agent,model,switching,rate-limit,pydantic-ai,langchain
Classifier: Development Status :: 3 - Alpha
Classifier: Intended Audience :: Developers
Classifier: License :: OSI Approved :: MIT License
Classifier: Operating System :: OS Independent
Classifier: Programming Language :: Python :: 3
Classifier: Programming Language :: Python :: 3.8
Classifier: Programming Language :: Python :: 3.9
Classifier: Programming Language :: Python :: 3.10
Classifier: Programming Language :: Python :: 3.11
Classifier: Topic :: Software Development :: Libraries :: Python Modules
Classifier: Topic :: Scientific/Engineering :: Artificial Intelligence
Requires-Python: >=3.8
License-File: LICENSE
Requires-Dist: pydantic-ai>=0.1.0
Requires-Dist: typing-extensions>=4.0.0
Provides-Extra: dev
Requires-Dist: pytest>=6.0; extra == "dev"
Requires-Dist: pytest-asyncio>=0.18.0; extra == "dev"
Requires-Dist: black>=21.0; extra == "dev"
Requires-Dist: flake8>=3.8; extra == "dev"
Requires-Dist: mypy>=0.800; extra == "dev"
Dynamic: author
Dynamic: home-page
Dynamic: license-file
Dynamic: requires-python
